pamauthserviceclient/__init__.py
pamauthserviceclient/client.py
PamAuthServiceClient-0.3.1.dist-info/AUTHORS.rst
PamAuthServiceClient-0.3.1.dist-info/LICENSE.txt
PamAuthServiceClient-0.3.1.dist-info/METADATA
PamAuthServiceClient-0.3.1.dist-info/WHEEL
PamAuthServiceClient-0.3.1.dist-info/top_level.txt
PamAuthServiceClient-0.3.1.dist-info/RECORD
