Metadata-Version: 2.1
Name: PamAuthServiceClient
Version: 0.3.1
Summary: Client for the PamAuthService
Home-page: https://in-stigler.htw-aalen.de/gitea/klauck/PamAuthServiceClient
Author: Sebastian Stigler
Author-email: sebastian.stigler@hs-aalen.de
License: mit
Project-URL: Documentation, https://in-stigler.htw-aalen.de/gitea/klauck/PamAuthServiceClient
Platform: any
Classifier: Development Status :: 4 - Beta
Classifier: License :: OSI Approved :: MIT License
Classifier: Programming Language :: Python
Classifier: Programming Language :: Python :: 3 :: Only
Classifier: Programming Language :: Python :: 3.6
Classifier: Programming Language :: Python :: 3.7
Classifier: Programming Language :: Python :: 3.8
Requires-Dist: cryptography
Requires-Dist: jsonschema
Requires-Dist: requests-unixsocket
Requires-Dist: requests
Requires-Dist: setuptools
Requires-Dist: recommonmark
Requires-Dist: sphinx-rtd-theme
Requires-Dist: Sphinx
Provides-Extra: testing
Requires-Dist: pytest ; extra == 'testing'
Requires-Dist: pytest-cov ; extra == 'testing'
